[
  {
    "symbol": "BTC/USDT",
    "side": "buy",
    "entry": 115105.52399999999,
    "exit": 115128.85566,
    "qty": 0.0026,
    "pnl": 0.9046198810387094,
    "reason": "SL_HALF",
    "regime": "trending",
    "score": "SCORE:3.0|TRENDING",
    "opened": "2025-09-12 08:00:00",
    "closed": "2025-09-15 00:00:00"
  },
  {
    "symbol": "BTC/USDT",
    "side": "buy",
    "entry": 115994.61832499999,
    "exit": 115664.413305,
    "qty": 0.0026,
    "pnl": 0.4288824924220914,
    "reason": "SL_HALF",
    "regime": "trending",
    "score": "SCORE:4.5|TRENDING",
    "opened": "2025-09-16 05:00:00",
    "closed": "2025-09-17 14:00:00"
  },
  {
    "symbol": "BTC/USDT",
    "side": "buy",
    "entry": 117699.36026999999,
    "exit": 116728.084875,
    "qty": 0.00258,
    "pnl": -2.868784204184433,
    "reason": "SL",
    "regime": "trending",
    "score": "SCORE:3.0|TRENDING",
    "opened": "2025-09-18 14:00:00",
    "closed": "2025-09-19 06:00:00"
  },
  {
    "symbol": "BTC/USDT",
    "side": "buy",
    "entry": 115758.31023,
    "exit": 114464.48363999999,
    "qty": 0.00255,
    "pnl": -3.6514986791211297,
    "reason": "SL",
    "regime": "trending",
    "score": "SCORE:3.0|TRENDING",
    "opened": "2025-09-20 06:00:00",
    "closed": "2025-09-22 00:00:00"
  },
  {
    "symbol": "BTC/USDT",
    "side": "buy",
    "entry": 113058.56103,
    "exit": 116169.33563999999,
    "qty": 0.00251,
    "pnl": 4.627365285780641,
    "reason": "TP",
    "regime": "trending",
    "score": "SCORE:4.0|TRENDING",
    "opened": "2025-09-30 12:00:00",
    "closed": "2025-10-01 08:00:00"
  },
  {
    "symbol": "BTC/USDT",
    "side": "buy",
    "entry": 118728.224445,
    "exit": 122319.17902499999,
    "qty": 0.00251,
    "pnl": 5.494495707348492,
    "reason": "TP",
    "regime": "trending",
    "score": "SCORE:3.0|TRENDING",
    "opened": "2025-10-02 08:00:00",
    "closed": "2025-10-03 15:00:00"
  },
  {
    "symbol": "BTC/USDT",
    "side": "buy",
    "entry": 121852.205655,
    "exit": 125235.39640499999,
    "qty": 0.00258,
    "pnl": 5.204534204166725,
    "reason": "TP",
    "regime": "trending",
    "score": "SCORE:4.0|TRENDING",
    "opened": "2025-10-04 15:00:00",
    "closed": "2025-10-05 04:00:00"
  },
  {
    "symbol": "BTC/USDT",
    "side": "buy",
    "entry": 126074.18558999998,
    "exit": 124720.86926999998,
    "qty": 0.00262,
    "pnl": -3.939938584639915,
    "reason": "SL",
    "regime": "trending",
    "score": "SCORE:4.5|TRENDING",
    "opened": "2025-10-06 18:00:00",
    "closed": "2025-10-06 23:00:00"
  },
  {
    "symbol": "BTC/USDT",
    "side": "sell",
    "entry": 106687.90936,
    "exit": 106750.12823500001,
    "qty": 0.00081,
    "pnl": 0.6335473335743034,
    "reason": "SL_HALF",
    "regime": "trending",
    "score": "SCORE:-5.0|TRENDING",
    "opened": "2025-10-17 06:00:00",
    "closed": "2025-10-17 15:00:00"
  },
  {
    "symbol": "BTC/USDT",
    "side": "sell",
    "entry": 107725.81015,
    "exit": 112114.43474000001,
    "qty": 0.00106,
    "pnl": -4.791760461150047,
    "reason": "SL",
    "regime": "trending",
    "score": "SCORE:-3.5|TRENDING",
    "opened": "2025-10-21 04:00:00",
    "closed": "2025-10-21 14:00:00"
  },
  {
    "symbol": "BTC/USDT",
    "side": "buy",
    "entry": 111316.99067999999,
    "exit": 114824.67364499999,
    "qty": 0.0026,
    "pnl": 6.067300113245915,
    "reason": "TP",
    "regime": "trending",
    "score": "SCORE:3.0|TRENDING",
    "opened": "2025-10-24 05:00:00",
    "closed": "2025-10-27 00:00:00"
  },
  {
    "symbol": "BTC/USDT",
    "side": "buy",
    "entry": 114018.650835,
    "exit": 113746.834995,
    "qty": 0.00284,
    "pnl": 0.8622316900402424,
    "reason": "SL_HALF",
    "regime": "trending",
    "score": "SCORE:3.0|TRENDING",
    "opened": "2025-10-28 00:00:00",
    "closed": "2025-10-28 19:00:00"
  },
  {
    "symbol": "BTC/USDT",
    "side": "sell",
    "entry": 109262.55139500002,
    "exit": 111141.391505,
    "qty": 0.00082,
    "pnl": -1.6490876301067918,
    "reason": "SL",
    "regime": "trending",
    "score": "SCORE:-5.0|TRENDING",
    "opened": "2025-10-31 00:00:00",
    "closed": "2025-11-02 11:00:00"
  },
  {
    "symbol": "BTC/USDT",
    "side": "sell",
    "entry": 107733.52629000001,
    "exit": 104163.65212,
    "qty": 0.00114,
    "pnl": 2.670509999299653,
    "reason": "TP",
    "regime": "trending",
    "score": "SCORE:-3.0|TRENDING",
    "opened": "2025-11-03 11:00:00",
    "closed": "2025-11-04 05:00:00"
  },
  {
    "symbol": "BTC/USDT",
    "side": "sell",
    "entry": 102068.93000500002,
    "exit": 104295.2263,
    "qty": 0.00068,
    "pnl": -1.5980780563724255,
    "reason": "SL",
    "regime": "trending",
    "score": "SCORE:-4.0|TRENDING",
    "opened": "2025-11-05 06:00:00",
    "closed": "2025-11-05 18:00:00"
  },
  {
    "symbol": "BTC/USDT",
    "side": "sell",
    "entry": 101429.04011,
    "exit": 102345.92144,
    "qty": 0.00086,
    "pnl": 0.28033069775188363,
    "reason": "SL_HALF",
    "regime": "trending",
    "score": "SCORE:-3.0|TRENDING",
    "opened": "2025-11-07 00:00:00",
    "closed": "2025-11-07 17:00:00"
  },
  {
    "symbol": "BTC/USDT",
    "side": "sell",
    "entry": 101938.65517499999,
    "exit": 103710.288915,
    "qty": 0.00129,
    "pnl": -2.444579807325666,
    "reason": "SL",
    "regime": "trending",
    "score": "SCORE:-3.0|TRENDING",
    "opened": "2025-11-08 19:00:00",
    "closed": "2025-11-09 15:00:00"
  },
  {
    "symbol": "BTC/USDT",
    "side": "sell",
    "entry": 105578.45436500001,
    "exit": 101391.888695,
    "qty": 0.00107,
    "pnl": 2.8751875588681797,
    "reason": "TP",
    "regime": "trending",
    "score": "SCORE:-3.0|TRENDING",
    "opened": "2025-11-10 21:00:00",
    "closed": "2025-11-12 16:00:00"
  },
  {
    "symbol": "BTC/USDT",
    "side": "sell",
    "entry": 99205.97220000002,
    "exit": 94002.61518000001,
    "qty": 0.00076,
    "pnl": 2.6642238362096573,
    "reason": "TP",
    "regime": "trending",
    "score": "SCORE:-3.0|TRENDING",
    "opened": "2025-11-14 01:00:00",
    "closed": "2025-11-16 18:00:00"
  },
  {
    "symbol": "BTC/USDT",
    "side": "sell",
    "entry": 91668.43285499999,
    "exit": 92863.64495000002,
    "qty": 0.00084,
    "pnl": 0.20457729782348721,
    "reason": "SL_HALF",
    "regime": "trending",
    "score": "SCORE:-3.0|TRENDING",
    "opened": "2025-11-18 01:00:00",
    "closed": "2025-11-18 15:00:00"
  },
  {
    "symbol": "BTC/USDT",
    "side": "sell",
    "entry": 89193.211085,
    "exit": 91509.18252000002,
    "qty": 0.00085,
    "pnl": -2.0607339404885616,
    "reason": "SL",
    "regime": "trending",
    "score": "SCORE:-3.5|TRENDING",
    "opened": "2025-11-19 18:00:00",
    "closed": "2025-11-19 23:00:00"
  },
  {
    "symbol": "BTC/USDT",
    "side": "sell",
    "entry": 85778.42933,
    "exit": 85836.890085,
    "qty": 0.00072,
    "pnl": 0.6822259750266829,
    "reason": "SL_HALF",
    "regime": "trending",
    "score": "SCORE:-3.0|TRENDING",
    "opened": "2025-11-21 03:00:00",
    "closed": "2025-11-23 01:00:00"
  },
  {
    "symbol": "BTC/USDT",
    "side": "sell",
    "entry": 87416.28999,
    "exit": 89044.51547,
    "qty": 0.00104,
    "pnl": -1.8034660418070334,
    "reason": "SL",
    "regime": "trending",
    "score": "SCORE:-3.0|TRENDING",
    "opened": "2025-11-24 03:00:00",
    "closed": "2025-11-24 20:00:00"
  },
  {
    "symbol": "BTC/USDT",
    "side": "sell",
    "entry": 87667.96409000001,
    "exit": 89785.874605,
    "qty": 0.00108,
    "pnl": -2.4023334436743555,
    "reason": "SL",
    "regime": "trending",
    "score": "SCORE:-3.0|TRENDING",
    "opened": "2025-11-26 02:00:00",
    "closed": "2025-11-26 17:00:00"
  },
  {
    "symbol": "BTC/USDT",
    "side": "sell",
    "entry": 86926.79486000001,
    "exit": 89227.35400500002,
    "qty": 0.00098,
    "pnl": -2.3581266016326263,
    "reason": "SL",
    "regime": "trending",
    "score": "SCORE:-5.0|TRENDING",
    "opened": "2025-12-02 04:00:00",
    "closed": "2025-12-02 14:00:00"
  },
  {
    "symbol": "BTC/USDT",
    "side": "sell",
    "entry": 92327.11335000001,
    "exit": 93896.26838000001,
    "qty": 0.00093,
    "pnl": -1.563226824905335,
    "reason": "SL",
    "regime": "trending",
    "score": "SCORE:-3.0|TRENDING",
    "opened": "2025-12-03 15:00:00",
    "closed": "2025-12-04 02:00:00"
  },
  {
    "symbol": "BTC/USDT",
    "side": "sell",
    "entry": 91318.49790999999,
    "exit": 94140.716095,
    "qty": 0.00094,
    "pnl": -2.7574840905988247,
    "reason": "SL",
    "regime": "trending",
    "score": "SCORE:-3.0|TRENDING",
    "opened": "2025-12-08 02:00:00",
    "closed": "2025-12-09 16:00:00"
  },
  {
    "symbol": "BTC/USDT",
    "side": "sell",
    "entry": 90294.83,
    "exit": 88792.56151,
    "qty": 0.00241,
    "pnl": 2.30006929516738,
    "reason": "TP",
    "regime": "trending",
    "score": "SCORE:-4.0|TRENDING",
    "opened": "2025-12-14 00:00:00",
    "closed": "2025-12-14 16:00:00"
  },
  {
    "symbol": "BTC/USDT",
    "side": "sell",
    "entry": 85978.499245,
    "exit": 87217.819275,
    "qty": 0.00114,
    "pnl": -1.531291116067683,
    "reason": "SL",
    "regime": "trending",
    "score": "SCORE:-3.0|TRENDING",
    "opened": "2025-12-16 07:00:00",
    "closed": "2025-12-16 11:00:00"
  },
  {
    "symbol": "BTC/USDT",
    "side": "sell",
    "entry": 89631.012075,
    "exit": 85786.30539000001,
    "qty": 0.00095,
    "pnl": 2.4474858139160793,
    "reason": "TP",
    "regime": "trending",
    "score": "SCORE:-4.0|TRENDING",
    "opened": "2025-12-17 14:00:00",
    "closed": "2025-12-17 18:00:00"
  },
  {
    "symbol": "BTC/USDT",
    "side": "sell",
    "entry": 84441.548105,
    "exit": 86847.944305,
    "qty": 0.00075,
    "pnl": -1.8818774215845022,
    "reason": "SL",
    "regime": "trending",
    "score": "SCORE:-5.5|TRENDING",
    "opened": "2025-12-18 19:00:00",
    "closed": "2025-12-19 03:00:00"
  },
  {
    "symbol": "BTC/USDT",
    "side": "sell",
    "entry": 88848.37359000002,
    "exit": 87626.26495000001,
    "qty": 0.00327,
    "pnl": 2.430503733624053,
    "reason": "TP",
    "regime": "ranging",
    "score": "SCORE:-3.0|RANGING",
    "opened": "2025-12-21 09:00:00",
    "closed": "2025-12-21 13:00:00"
  },
  {
    "symbol": "BTC/USDT",
    "side": "sell",
    "entry": 87181.657365,
    "exit": 89155.39000500001,
    "qty": 0.00196,
    "pnl": -4.075888342107124,
    "reason": "SL",
    "regime": "trending",
    "score": "SCORE:-3.0|TRENDING",
    "opened": "2025-12-25 23:00:00",
    "closed": "2025-12-26 02:00:00"
  },
  {
    "symbol": "BTC/USDT",
    "side": "sell",
    "entry": 87470.46289000001,
    "exit": 88251.542155,
    "qty": 0.00185,
    "pnl": -1.6400480658499372,
    "reason": "SL",
    "regime": "trending",
    "score": "SCORE:-3.0|TRENDING",
    "opened": "2025-12-27 03:00:00",
    "closed": "2025-12-29 00:00:00"
  },
  {
    "symbol": "BTC/USDT",
    "side": "sell",
    "entry": 87459.09857500001,
    "exit": 88831.392085,
    "qty": 0.00177,
    "pnl": -2.6161800137809,
    "reason": "SL",
    "regime": "trending",
    "score": "SCORE:-3.0|TRENDING",
    "opened": "2025-12-30 07:00:00",
    "closed": "2025-12-30 14:00:00"
  },
  {
    "symbol": "BTC/USDT",
    "side": "sell",
    "entry": 90892.660935,
    "exit": 90968.143175,
    "qty": 0.00314,
    "pnl": -0.00038208369078374105,
    "reason": "SL_HALF",
    "regime": "ranging",
    "score": "SCORE:-3.5|RANGING",
    "opened": "2026-01-11 12:00:00",
    "closed": "2026-01-11 23:00:00"
  },
  {
    "symbol": "BTC/USDT",
    "side": "sell",
    "entry": 93403.26500500001,
    "exit": 95709.33139500002,
    "qty": 0.00117,
    "pnl": -2.830854718972809,
    "reason": "SL",
    "regime": "trending",
    "score": "SCORE:-3.0|TRENDING",
    "opened": "2026-01-13 15:00:00",
    "closed": "2026-01-13 22:00:00"
  },
  {
    "symbol": "BTC/USDT",
    "side": "sell",
    "entry": 92016.578695,
    "exit": 89730.57227,
    "qty": 0.00173,
    "pnl": 2.473524695199166,
    "reason": "TP",
    "regime": "trending",
    "score": "SCORE:-5.5|TRENDING",
    "opened": "2026-01-20 04:00:00",
    "closed": "2026-01-20 17:00:00"
  },
  {
    "symbol": "BTC/USDT",
    "side": "sell",
    "entry": 87888.41381000001,
    "exit": 90310.38222,
    "qty": 0.00084,
    "pnl": -2.124265657599109,
    "reason": "SL",
    "regime": "trending",
    "score": "SCORE:-5.0|TRENDING",
    "opened": "2026-01-21 17:00:00",
    "closed": "2026-01-21 19:00:00"
  },
  {
    "symbol": "BTC/USDT",
    "side": "sell",
    "entry": 88915.86982500002,
    "exit": 88876.5395,
    "qty": 0.00289,
    "pnl": 0.45956547149489313,
    "reason": "SL_HALF",
    "regime": "trending",
    "score": "SCORE:-3.5|TRENDING",
    "opened": "2026-01-25 03:00:00",
    "closed": "2026-01-25 13:00:00"
  },
  {
    "symbol": "BTC/USDT",
    "side": "sell",
    "entry": 88134.01095000001,
    "exit": 89351.46192,
    "qty": 0.00133,
    "pnl": -1.7608431974502479,
    "reason": "SL",
    "regime": "trending",
    "score": "SCORE:-3.0|TRENDING",
    "opened": "2026-01-26 14:00:00",
    "closed": "2026-01-27 20:00:00"
  },
  {
    "symbol": "BTC/USDT",
    "side": "sell",
    "entry": 87863.10647,
    "exit": 84219.52917000001,
    "qty": 0.00103,
    "pnl": 2.428620580155922,
    "reason": "TP",
    "regime": "trending",
    "score": "SCORE:-4.5|TRENDING",
    "opened": "2026-01-29 02:00:00",
    "closed": "2026-01-29 17:00:00"
  },
  {
    "symbol": "BTC/USDT",
    "side": "sell",
    "entry": 84200.868505,
    "exit": 78854.47304,
    "qty": 0.00071,
    "pnl": 2.4917639489585093,
    "reason": "TP",
    "regime": "trending",
    "score": "SCORE:-3.0|TRENDING",
    "opened": "2026-01-30 19:00:00",
    "closed": "2026-01-31 17:00:00"
  },
  {
    "symbol": "BTC/USDT",
    "side": "sell",
    "entry": 77136.19261,
    "exit": 78810.63497,
    "qty": 0.0008,
    "pnl": -1.4144083652384007,
    "reason": "SL",
    "regime": "trending",
    "score": "SCORE:-4.5|TRENDING",
    "opened": "2026-02-01 19:00:00",
    "closed": "2026-02-02 15:00:00"
  },
  {
    "symbol": "BTC/USDT",
    "side": "sell",
    "entry": 78093.263835,
    "exit": 73102.560435,
    "qty": 0.00089,
    "pnl": 2.819541680485044,
    "reason": "TP",
    "regime": "trending",
    "score": "SCORE:-3.0|TRENDING",
    "opened": "2026-02-03 15:00:00",
    "closed": "2026-02-03 18:00:00"
  },
  {
    "symbol": "BTC/USDT",
    "side": "sell",
    "entry": 73389.24702000001,
    "exit": 67455.32546500002,
    "qty": 0.00066,
    "pnl": 2.5921001034970534,
    "reason": "TP",
    "regime": "trending",
    "score": "SCORE:-5.0|TRENDING",
    "opened": "2026-02-04 18:00:00",
    "closed": "2026-02-05 15:00:00"
  },
  {
    "symbol": "BTC/USDT",
    "side": "sell",
    "entry": 70718.153235,
    "exit": 69013.46600500001,
    "qty": 0.00046,
    "pnl": 1.0505863711622712,
    "reason": "EXPIRY",
    "regime": "trending",
    "score": "SCORE:-3.0|TRENDING",
    "opened": "2026-02-06 17:00:00",
    "closed": "2026-02-13 17:00:00"
  },
  {
    "symbol": "BTC/USDT",
    "side": "sell",
    "entry": 68390.60759000001,
    "exit": 69728.35838,
    "qty": 0.00141,
    "pnl": -2.0030772591106074,
    "reason": "SL",
    "regime": "trending",
    "score": "SCORE:-3.0|TRENDING",
    "opened": "2026-02-16 03:00:00",
    "closed": "2026-02-16 12:00:00"
  },
  {
    "symbol": "BTC/USDT",
    "side": "sell",
    "entry": 66375.61559000002,
    "exit": 67756.20495000001,
    "qty": 0.00128,
    "pnl": -1.8701676189747176,
    "reason": "SL",
    "regime": "trending",
    "score": "SCORE:-3.0|TRENDING",
    "opened": "2026-02-18 22:00:00",
    "closed": "2026-02-20 05:00:00"
  },
  {
    "symbol": "BTC/USDT",
    "side": "sell",
    "entry": 67350.797755,
    "exit": 64395.436175,
    "qty": 0.00238,
    "pnl": 4.047860928220025,
    "reason": "TP",
    "regime": "trending",
    "score": "SCORE:-3.5|TRENDING",
    "opened": "2026-02-22 17:00:00",
    "closed": "2026-02-23 01:00:00"
  },
  {
    "symbol": "BTC/USDT",
    "side": "sell",
    "entry": 64077.755095,
    "exit": 65863.80162500001,
    "qty": 0.00119,
    "pnl": -2.218173642198088,
    "reason": "SL",
    "regime": "trending",
    "score": "SCORE:-3.0|TRENDING",
    "opened": "2026-02-24 02:00:00",
    "closed": "2026-02-25 01:00:00"
  },
  {
    "symbol": "BTC/USDT",
    "side": "sell",
    "entry": 68182.75157000001,
    "exit": 63184.40199500001,
    "qty": 0.00097,
    "pnl": 3.0567704439763252,
    "reason": "TP",
    "regime": "trending",
    "score": "SCORE:-3.0|TRENDING",
    "opened": "2026-02-26 03:00:00",
    "closed": "2026-02-28 06:00:00"
  },
  {
    "symbol": "BTC/USDT",
    "side": "sell",
    "entry": 65946.62019500001,
    "exit": 69095.6349,
    "qty": 0.00103,
    "pnl": -3.326941259798704,
    "reason": "SL",
    "regime": "trending",
    "score": "SCORE:-3.0|TRENDING",
    "opened": "2026-03-01 17:00:00",
    "closed": "2026-03-02 15:00:00"
  },
  {
    "symbol": "BTC/USDT",
    "side": "sell",
    "entry": 67205.1806,
    "exit": 67877.20442000001,
    "qty": 0.00154,
    "pnl": 0.07356080033919543,
    "reason": "SL_HALF",
    "regime": "trending",
    "score": "SCORE:-3.0|TRENDING",
    "opened": "2026-03-08 20:00:00",
    "closed": "2026-03-09 05:00:00"
  },
  {
    "symbol": "BTC/USDT",
    "side": "sell",
    "entry": 70370.80699499999,
    "exit": 71785.10949,
    "qty": 0.00101,
    "pnl": -1.5145920053399209,
    "reason": "SL",
    "regime": "trending",
    "score": "SCORE:-4.0|TRENDING",
    "opened": "2026-03-10 07:00:00",
    "closed": "2026-03-13 08:00:00"
  },
  {
    "symbol": "BTC/USDT",
    "side": "sell",
    "entry": 69696.34439500001,
    "exit": 70087.088925,
    "qty": 0.00122,
    "pnl": 0.35979944881111786,
    "reason": "SL_HALF",
    "regime": "trending",
    "score": "SCORE:-4.5|TRENDING",
    "opened": "2026-03-20 14:00:00",
    "closed": "2026-03-23 11:00:00"
  },
  {
    "symbol": "BTC/USDT",
    "side": "sell",
    "entry": 69442.131565,
    "exit": 70805.329625,
    "qty": 0.00116,
    "pnl": -1.6789219825882344,
    "reason": "SL",
    "regime": "trending",
    "score": "SCORE:-5.5|TRENDING",
    "opened": "2026-03-24 16:00:00",
    "closed": "2026-03-25 00:00:00"
  },
  {
    "symbol": "BTC/USDT",
    "side": "sell",
    "entry": 66586.45012,
    "exit": 67646.609775,
    "qty": 0.00124,
    "pnl": -1.414467368761893,
    "reason": "SL",
    "regime": "trending",
    "score": "SCORE:-5.5|TRENDING",
    "opened": "2026-03-27 12:00:00",
    "closed": "2026-03-30 11:00:00"
  },
  {
    "symbol": "BTC/USDT",
    "side": "sell",
    "entry": 66554.156275,
    "exit": 67820.122975,
    "qty": 0.0011,
    "pnl": -1.481250394305005,
    "reason": "SL",
    "regime": "trending",
    "score": "SCORE:-3.0|TRENDING",
    "opened": "2026-03-31 14:00:00",
    "closed": "2026-03-31 18:00:00"
  },
  {
    "symbol": "BTC/USDT",
    "side": "sell",
    "entry": 67325.59036500001,
    "exit": 67349.96817000001,
    "qty": 0.00118,
    "pnl": 0.5620003472192208,
    "reason": "SL_HALF",
    "regime": "trending",
    "score": "SCORE:-3.5|TRENDING",
    "opened": "2026-04-02 01:00:00",
    "closed": "2026-04-04 15:00:00"
  },
  {
    "symbol": "BTC/USDT",
    "side": "sell",
    "entry": 67624.52082500001,
    "exit": 68304.26078499999,
    "qty": 0.00348,
    "pnl": -2.6493143568016,
    "reason": "SL",
    "regime": "ranging",
    "score": "SCORE:-5.5|RANGING",
    "opened": "2026-04-05 20:00:00",
    "closed": "2026-04-05 22:00:00"
  },
  {
    "symbol": "BTC/USDT",
    "side": "sell",
    "entry": 76425.718025,
    "exit": 77231.12512,
    "qty": 0.0019,
    "pnl": -1.7054422816853045,
    "reason": "SL",
    "regime": "trending",
    "score": "SCORE:-4.0|TRENDING",
    "opened": "2026-04-28 20:00:00",
    "closed": "2026-04-29 04:00:00"
  },
  {
    "symbol": "BTC/USDT",
    "side": "sell",
    "entry": 75562.289955,
    "exit": 76647.78693500001,
    "qty": 0.00132,
    "pnl": -1.5534063944968943,
    "reason": "SL",
    "regime": "trending",
    "score": "SCORE:-5.0|TRENDING",
    "opened": "2026-04-30 05:00:00",
    "closed": "2026-05-01 01:00:00"
  },
  {
    "symbol": "BTC/USDT",
    "side": "sell",
    "entry": 78314.753035,
    "exit": 79137.701355,
    "qty": 0.00166,
    "pnl": -1.5229168557724333,
    "reason": "SL",
    "regime": "trending",
    "score": "SCORE:-3.0|TRENDING",
    "opened": "2026-05-02 02:00:00",
    "closed": "2026-05-03 22:00:00"
  },
  {
    "symbol": "BTC/USDT",
    "side": "sell",
    "entry": 79540.21,
    "exit": 80924.36757500001,
    "qty": 0.00163,
    "pnl": -2.4131112041183576,
    "reason": "SL",
    "regime": "trending",
    "score": "SCORE:-3.0|TRENDING",
    "opened": "2026-05-14 00:00:00",
    "closed": "2026-05-14 14:00:00"
  },
  {
    "symbol": "BTC/USDT",
    "side": "sell",
    "entry": 79110.794815,
    "exit": 76355.453175,
    "qty": 0.00113,
    "pnl": 2.057419619080133,
    "reason": "TP",
    "regime": "trending",
    "score": "SCORE:-4.5|TRENDING",
    "opened": "2026-05-15 14:00:00",
    "closed": "2026-05-18 14:00:00"
  },
  {
    "symbol": "BTC/USDT",
    "side": "sell",
    "entry": 76946.11769500001,
    "exit": 77830.44531000001,
    "qty": 0.00163,
    "pnl": -1.5928254910688933,
    "reason": "SL",
    "regime": "trending",
    "score": "SCORE:-3.0|TRENDING",
    "opened": "2026-05-21 14:00:00",
    "closed": "2026-05-21 17:00:00"
  },
  {
    "symbol": "BTC/USDT",
    "side": "sell",
    "entry": 75940.84058500001,
    "exit": 75945.458275,
    "qty": 0.00163,
    "pnl": 0.4680333581632645,
    "reason": "SL_HALF",
    "regime": "trending",
    "score": "SCORE:-4.0|TRENDING",
    "opened": "2026-05-22 21:00:00",
    "closed": "2026-05-23 19:00:00"
  },
  {
    "symbol": "BTC/USDT",
    "side": "sell",
    "entry": 76113.06443,
    "exit": 76765.58800500001,
    "qty": 0.0018,
    "pnl": -1.3396513796298248,
    "reason": "SL",
    "regime": "trending",
    "score": "SCORE:-4.5|TRENDING",
    "opened": "2026-05-24 21:00:00",
    "closed": "2026-05-24 22:00:00"
  },
  {
    "symbol": "BTC/USDT",
    "side": "sell",
    "entry": 76479.84095000001,
    "exit": 73221.380995,
    "qty": 0.00127,
    "pnl": 2.563662374195623,
    "reason": "TP",
    "regime": "trending",
    "score": "SCORE:-5.0|TRENDING",
    "opened": "2026-05-26 15:00:00",
    "closed": "2026-05-28 03:00:00"
  },
  {
    "symbol": "BTC/USDT",
    "side": "sell",
    "entry": 73264.86924000001,
    "exit": 74053.79458,
    "qty": 0.00147,
    "pnl": -1.289655311289221,
    "reason": "SL",
    "regime": "trending",
    "score": "SCORE:-3.0|TRENDING",
    "opened": "2026-05-29 03:00:00",
    "closed": "2026-05-31 02:00:00"
  },
  {
    "symbol": "BTC/USDT",
    "side": "sell",
    "entry": 73099.17213,
    "exit": 71094.05519,
    "qty": 0.00181,
    "pnl": 2.284415645318115,
    "reason": "TP",
    "regime": "trending",
    "score": "SCORE:-3.5|TRENDING",
    "opened": "2026-06-01 06:00:00",
    "closed": "2026-06-01 15:00:00"
  },
  {
    "symbol": "BTC/USDT",
    "side": "sell",
    "entry": 67270.62786000001,
    "exit": 67296.34499499999,
    "qty": 0.00111,
    "pnl": 0.5229770854713861,
    "reason": "SL_HALF",
    "regime": "trending",
    "score": "SCORE:-6.5|TRENDING",
    "opened": "2026-06-02 15:00:00",
    "closed": "2026-06-03 05:00:00"
  },
  {
    "symbol": "BTC/USDT",
    "side": "sell",
    "entry": 63995.976005000004,
    "exit": 59366.292005,
    "qty": 0.00071,
    "pnl": 2.2110637495750094,
    "reason": "TP",
    "regime": "trending",
    "score": "SCORE:-4.0|TRENDING",
    "opened": "2026-06-04 06:00:00",
    "closed": "2026-06-05 18:00:00"
  },
  {
    "symbol": "BTC/USDT",
    "side": "sell",
    "entry": 60569.709995000005,
    "exit": 61859.97454,
    "qty": 0.00099,
    "pnl": -1.3500851321637883,
    "reason": "SL",
    "regime": "trending",
    "score": "SCORE:-3.0|TRENDING",
    "opened": "2026-06-06 19:00:00",
    "closed": "2026-06-07 04:00:00"
  },
  {
    "symbol": "BTC/USDT",
    "side": "sell",
    "entry": 63697.09552,
    "exit": 61003.52298,
    "qty": 0.00119,
    "pnl": 2.1502016106276876,
    "reason": "TP",
    "regime": "trending",
    "score": "SCORE:-3.0|TRENDING",
    "opened": "2026-06-08 21:00:00",
    "closed": "2026-06-10 11:00:00"
  },
  {
    "symbol": "BTC/USDT",
    "side": "sell",
    "entry": 63046.031215,
    "exit": 63967.990005,
    "qty": 0.00138,
    "pnl": -1.3774707397701556,
    "reason": "SL",
    "regime": "trending",
    "score": "SCORE:-3.0|TRENDING",
    "opened": "2026-06-11 13:00:00",
    "closed": "2026-06-12 14:00:00"
  },
  {
    "symbol": "ETH/USDT",
    "side": "buy",
    "entry": 4520.158949999999,
    "exit": 4697.5075799999995,
    "qty": 0.0553,
    "pnl": 6.4125848585954275,
    "reason": "TP",
    "regime": "trending",
    "score": "SCORE:4.0|TRENDING",
    "opened": "2025-09-12 08:00:00",
    "closed": "2025-09-12 22:00:00"
  },
  {
    "symbol": "ETH/USDT",
    "side": "buy",
    "entry": 4660.859264999999,
    "exit": 4584.51111,
    "qty": 0.0596,
    "pnl": -4.880964482609927,
    "reason": "SL",
    "regime": "trending",
    "score": "SCORE:4.0|TRENDING",
    "opened": "2025-09-13 22:00:00",
    "closed": "2025-09-14 15:00:00"
  },
  {
    "symbol": "ETH/USDT",
    "side": "buy",
    "entry": 4516.27701,
    "exit": 4448.933355,
    "qty": 0.0597,
    "pnl": -4.3415500387742805,
    "reason": "SL",
    "regime": "trending",
    "score": "SCORE:3.0|TRENDING",
    "opened": "2025-09-16 02:00:00",
    "closed": "2025-09-16 14:00:00"
  },
  {
    "symbol": "ETH/USDT",
    "side": "buy",
    "entry": 4435.986885,
    "exit": 4592.8252649999995,
    "qty": 0.0331,
    "pnl": 4.151597168465528,
    "reason": "TP",
    "regime": "volatile",
    "score": "SCORE:3.0|VOLATILE",
    "opened": "2025-09-17 17:00:00",
    "closed": "2025-09-17 23:00:00"
  },
  {
    "symbol": "ETH/USDT",
    "side": "buy",
    "entry": 4160.49921,
    "exit": 4101.159554999999,
    "qty": 0.0635,
    "pnl": -4.082837291446543,
    "reason": "SL",
    "regime": "trending",
    "score": "SCORE:4.0|TRENDING",
    "opened": "2025-09-30 12:00:00",
    "closed": "2025-09-30 16:00:00"
  },
  {
    "symbol": "ETH/USDT",
    "side": "buy",
    "entry": 4326.732284999999,
    "exit": 4537.017374999999,
    "qty": 0.0463,
    "pnl": 6.374459955404326,
    "reason": "TP",
    "regime": "trending",
    "score": "SCORE:4.0|TRENDING",
    "opened": "2025-10-01 16:00:00",
    "closed": "2025-10-03 15:00:00"
  },
  {
    "symbol": "ETH/USDT",
    "side": "buy",
    "entry": 4486.742249999999,
    "exit": 4640.188934999999,
    "qty": 0.0692,
    "pnl": 6.793276472806028,
    "reason": "TP",
    "regime": "trending",
    "score": "SCORE:5.0|TRENDING",
    "opened": "2025-10-04 21:00:00",
    "closed": "2025-10-06 13:00:00"
  },
  {
    "symbol": "ETH/USDT",
    "side": "buy",
    "entry": 4706.982315,
    "exit": 4595.13642,
    "qty": 0.0533,
    "pnl": -6.25886796064532,
    "reason": "SL",
    "regime": "trending",
    "score": "SCORE:3.0|TRENDING",
    "opened": "2025-10-07 13:00:00",
    "closed": "2025-10-07 14:00:00"
  },
  {
    "symbol": "ETH/USDT",
    "side": "buy",
    "entry": 4330.164,
    "exit": 4105.161555,
    "qty": 0.029,
    "pnl": -6.671845569657003,
    "reason": "SL",
    "regime": "volatile",
    "score": "SCORE:3.0|VOLATILE",
    "opened": "2025-10-09 08:00:00",
    "closed": "2025-10-10 15:00:00"
  },
  {
    "symbol": "ETH/USDT",
    "side": "buy",
    "entry": 4074.9264449999996,
    "exit": 4207.592745,
    "qty": 0.0684,
    "pnl": 5.974188171127577,
    "reason": "TP",
    "regime": "trending",
    "score": "SCORE:4.5|TRENDING",
    "opened": "2025-10-26 12:00:00",
    "closed": "2025-10-27 02:00:00"
  },
  {
    "symbol": "ETH/USDT",
    "side": "buy",
    "entry": 4096.36716,
    "exit": 3981.26964,
    "qty": 0.0487,
    "pnl": -5.8412777712959905,
    "reason": "SL",
    "regime": "trending",
    "score": "SCORE:3.0|TRENDING",
    "opened": "2025-10-28 03:00:00",
    "closed": "2025-10-28 20:00:00"
  },
  {
    "symbol": "ETH/USDT",
    "side": "buy",
    "entry": 3924.52128,
    "exit": 3820.18914,
    "qty": 0.0362,
    "pnl": -3.9450385783223996,
    "reason": "SL",
    "regime": "trending",
    "score": "SCORE:3.0|TRENDING",
    "opened": "2025-10-30 00:00:00",
    "closed": "2025-10-30 12:00:00"
  },
  {
    "symbol": "ETH/USDT",
    "side": "sell",
    "entry": 3301.6483500000004,
    "exit": 3436.211035,
    "qty": 0.0105,
    "pnl": -1.455356706625494,
    "reason": "SL",
    "regime": "trending",
    "score": "SCORE:-4.5|TRENDING",
    "opened": "2025-11-04 18:00:00",
    "closed": "2025-11-05 16:00:00"
  },
  {
    "symbol": "ETH/USDT",
    "side": "sell",
    "entry": 3274.9517050000004,
    "exit": 3383.937185,
    "qty": 0.0129,
    "pnl": -1.4574524920085978,
    "reason": "SL",
    "regime": "trending",
    "score": "SCORE:-4.5|TRENDING",
    "opened": "2025-11-06 16:00:00",
    "closed": "2025-11-07 17:00:00"
  },
  {
    "symbol": "ETH/USDT",
    "side": "sell",
    "entry": 3374.1121000000003,
    "exit": 3439.85921,
    "qty": 0.0213,
    "pnl": -1.4874959963417955,
    "reason": "SL",
    "regime": "trending",
    "score": "SCORE:-3.0|TRENDING",
    "opened": "2025-11-09 03:00:00",
    "closed": "2025-11-09 12:00:00"
  },
  {
    "symbol": "ETH/USDT",
    "side": "buy",
    "entry": 3573.7359749999996,
    "exit": 3482.84055,
    "qty": 0.0431,
    "pnl": -4.100075886436487,
    "reason": "SL",
    "regime": "trending",
    "score": "SCORE:3.0|TRENDING",
    "opened": "2025-11-10 20:00:00",
    "closed": "2025-11-11 15:00:00"
  },
  {
    "symbol": "ETH/USDT",
    "side": "sell",
    "entry": 3124.8567900000003,
    "exit": 3246.6358700000005,
    "qty": 0.0103,
    "pnl": -1.2937003486388026,
    "reason": "SL",
    "regime": "trending",
    "score": "SCORE:-4.5|TRENDING",
    "opened": "2025-11-14 12:00:00",
    "closed": "2025-11-16 09:00:00"
  },
  {
    "symbol": "ETH/USDT",
    "side": "sell",
    "entry": 3182.10815,
    "exit": 2980.778865,
    "qty": 0.0162,
    "pnl": 2.1691111920611745,
    "reason": "TP",
    "regime": "trending",
    "score": "SCORE:-3.0|TRENDING",
    "opened": "2025-11-17 12:00:00",
    "closed": "2025-11-17 19:00:00"
  },
  {
    "symbol": "ETH/USDT",
    "side": "sell",
    "entry": 3103.54745,
    "exit": 2880.21917,
    "qty": 0.0145,
    "pnl": 2.1795983405905623,
    "reason": "TP",
    "regime": "trending",
    "score": "SCORE:-3.0|TRENDING",
    "opened": "2025-11-19 01:00:00",
    "closed": "2025-11-19 19:00:00"
  },
  {
    "symbol": "ETH/USDT",
    "side": "sell",
    "entry": 2859.64946,
    "exit": 2865.536515,
    "qty": 0.0128,
    "pnl": 0.5430523070051053,
    "reason": "SL_HALF",
    "regime": "trending",
    "score": "SCORE:-3.0|TRENDING",
    "opened": "2025-11-21 00:00:00",
    "closed": "2025-11-24 05:00:00"
  },
  {
    "symbol": "ETH/USDT",
    "side": "sell",
    "entry": 2870.26415,
    "exit": 2934.941795,
    "qty": 0.0201,
    "pnl": -1.3700314481967042,
    "reason": "SL",
    "regime": "trending",
    "score": "SCORE:-3.0|TRENDING",
    "opened": "2025-11-25 08:00:00",
    "closed": "2025-11-25 17:00:00"
  },
  {
    "symbol": "ETH/USDT",
    "side": "sell",
    "entry": 2794.28216,
    "exit": 2893.53251,
    "qty": 0.0202,
    "pnl": -2.073793383800396,
    "reason": "SL",
    "regime": "trending",
    "score": "SCORE:-4.0|TRENDING",
    "opened": "2025-12-02 00:00:00",
    "closed": "2025-12-02 14:00:00"
  },
  {
    "symbol": "ETH/USDT",
    "side": "sell",
    "entry": 3196.6908550000003,
    "exit": 3006.0262350000003,
    "qty": 0.0163,
    "pnl": 2.101518584564328,
    "reason": "TP",
    "regime": "trending",
    "score": "SCORE:-3.0|TRENDING",
    "opened": "2025-12-04 00:00:00",
    "closed": "2025-12-05 18:00:00"
  },
  {
    "symbol": "ETH/USDT",
    "side": "sell",
    "entry": 3110.0741850000004,
    "exit": 3118.7098650000003,
    "qty": 0.038,
    "pnl": 0.33539755695659207,
    "reason": "SL_HALF",
    "regime": "trending",
    "score": "SCORE:-3.0|TRENDING",
    "opened": "2025-12-14 05:00:00",
    "closed": "2025-12-15 02:00:00"
  },
  {
    "symbol": "ETH/USDT",
    "side": "sell",
    "entry": 2944.377075,
    "exit": 2962.6179500000003,
    "qty": 0.0183,
    "pnl": 0.39382888815832995,
    "reason": "SL_HALF",
    "regime": "trending",
    "score": "SCORE:-4.0|TRENDING",
    "opened": "2025-12-16 02:00:00",
    "closed": "2025-12-18 13:00:00"
  },
  {
    "symbol": "ETH/USDT",
    "side": "sell",
    "entry": 2994.0222400000002,
    "exit": 2930.0642350000003,
    "qty": 0.0167,
    "pnl": 1.1016741413953728,
    "reason": "EXPIRY",
    "regime": "trending",
    "score": "SCORE:-3.0|TRENDING",
    "opened": "2025-12-19 20:00:00",
    "closed": "2025-12-26 20:00:00"
  },
  {
    "symbol": "ETH/USDT",
    "side": "sell",
    "entry": 2928.01526,
    "exit": 2947.5754750000006,
    "qty": 0.0662,
    "pnl": -1.5282646969942282,
    "reason": "SL",
    "regime": "trending",
    "score": "SCORE:-5.0|TRENDING",
    "opened": "2025-12-27 20:00:00",
    "closed": "2025-12-27 23:00:00"
  },
  {
    "symbol": "ETH/USDT",
    "side": "sell",
    "entry": 2949.434545,
    "exit": 2979.4595249999998,
    "qty": 0.0688,
    "pnl": -2.310463371209578,
    "reason": "SL",
    "regime": "ranging",
    "score": "SCORE:-2.5|RANGING",
    "opened": "2025-12-28 23:00:00",
    "closed": "2025-12-29 01:00:00"
  },
  {
    "symbol": "ETH/USDT",
    "side": "sell",
    "entry": 3095.441505,
    "exit": 3127.87528,
    "qty": 0.038,
    "pnl": -1.3743750726980162,
    "reason": "SL",
    "regime": "trending",
    "score": "SCORE:-3.0|TRENDING",
    "opened": "2026-01-10 11:00:00",
    "closed": "2026-01-11 16:00:00"
  },
  {
    "symbol": "ETH/USDT",
    "side": "sell",
    "entry": 3045.966255,
    "exit": 2890.13421,
    "qty": 0.024,
    "pnl": 2.3899588048916858,
    "reason": "TP",
    "regime": "trending",
    "score": "SCORE:-4.5|TRENDING",
    "opened": "2026-01-20 14:00:00",
    "closed": "2026-01-21 16:00:00"
  },
  {
    "symbol": "ETH/USDT",
    "side": "sell",
    "entry": 2944.76688,
    "exit": 2943.777375,
    "qty": 0.0174,
    "pnl": 0.5635029398514488,
    "reason": "SL_HALF",
    "regime": "trending",
    "score": "SCORE:-3.0|TRENDING",
    "opened": "2026-01-22 16:00:00",
    "closed": "2026-01-27 02:00:00"
  },
  {
    "symbol": "ETH/USDT",
    "side": "sell",
    "entry": 2745.64649,
    "exit": 2537.4206550000004,
    "qty": 0.0178,
    "pnl": 2.415725889662972,
    "reason": "TP",
    "regime": "trending",
    "score": "SCORE:-3.0|TRENDING",
    "opened": "2026-01-30 05:00:00",
    "closed": "2026-01-31 14:00:00"
  },
  {
    "symbol": "ETH/USDT",
    "side": "sell",
    "entry": 2371.8834650000003,
    "exit": 2371.523645,
    "qty": 0.0145,
    "pnl": 0.5937739123974958,
    "reason": "SL_HALF",
    "regime": "trending",
    "score": "SCORE:-4.0|TRENDING",
    "opened": "2026-02-01 14:00:00",
    "closed": "2026-02-02 15:00:00"
  },
  {
    "symbol": "ETH/USDT",
    "side": "sell",
    "entry": 2302.0484,
    "exit": 2102.9779850000004,
    "qty": 0.0163,
    "pnl": 2.214665904476564,
    "reason": "TP",
    "regime": "trending",
    "score": "SCORE:-3.0|TRENDING",
    "opened": "2026-02-03 15:00:00",
    "closed": "2026-02-05 04:00:00"
  },
  {
    "symbol": "ETH/USDT",
    "side": "sell",
    "entry": 1908.075485,
    "exit": 2035.1519150000001,
    "qty": 0.0103,
    "pnl": -1.333256374332001,
    "reason": "SL",
    "regime": "trending",
    "score": "SCORE:-4.0|TRENDING",
    "opened": "2026-02-06 04:00:00",
    "closed": "2026-02-06 16:00:00"
  },
  {
    "symbol": "ETH/USDT",
    "side": "sell",
    "entry": 2049.2748500000002,
    "exit": 2060.399285,
    "qty": 0.0146,
    "pnl": 0.5247657434942075,
    "reason": "SL_HALF",
    "regime": "trending",
    "score": "SCORE:-3.0|TRENDING",
    "opened": "2026-02-07 16:00:00",
    "closed": "2026-02-13 16:00:00"
  },
  {
    "symbol": "ETH/USDT",
    "side": "sell",
    "entry": 2009.9945,
    "exit": 2017.0609650000001,
    "qty": 0.0297,
    "pnl": 0.4777212288861528,
    "reason": "SL_HALF",
    "regime": "trending",
    "score": "SCORE:-3.5|TRENDING",
    "opened": "2026-02-15 12:00:00",
    "closed": "2026-02-18 07:00:00"
  },
  {
    "symbol": "ETH/USDT",
    "side": "sell",
    "entry": 1948.60521,
    "exit": 1980.1894100000002,
    "qty": 0.0403,
    "pnl": -1.3678415139116098,
    "reason": "SL",
    "regime": "trending",
    "score": "SCORE:-4.0|TRENDING",
    "opened": "2026-02-19 11:00:00",
    "closed": "2026-02-21 13:00:00"
  },
  {
    "symbol": "ETH/USDT",
    "side": "sell",
    "entry": 1940.0195050000002,
    "exit": 1855.9515600000002,
    "qty": 0.0651,
    "pnl": 3.2517612903385746,
    "reason": "TP",
    "regime": "trending",
    "score": "SCORE:-4.0|TRENDING",
    "opened": "2026-02-22 20:00:00",
    "closed": "2026-02-23 01:00:00"
  },
  {
    "symbol": "ETH/USDT",
    "side": "sell",
    "entry": 1840.0295250000001,
    "exit": 1917.38083,
    "qty": 0.0315,
    "pnl": -2.5075811632094975,
    "reason": "SL",
    "regime": "trending",
    "score": "SCORE:-3.0|TRENDING",
    "opened": "2026-02-24 01:00:00",
    "closed": "2026-02-25 01:00:00"
  },
  {
    "symbol": "ETH/USDT",
    "side": "sell",
    "entry": 1935.901565,
    "exit": 1976.4912600000002,
    "qty": 0.0409,
    "pnl": -1.756128645425514,
    "reason": "SL",
    "regime": "trending",
    "score": "SCORE:-4.0|TRENDING",
    "opened": "2026-03-08 16:00:00",
    "closed": "2026-03-09 03:00:00"
  },
  {
    "symbol": "ETH/USDT",
    "side": "sell",
    "entry": 2025.7866000000001,
    "exit": 2078.310325,
    "qty": 0.0253,
    "pnl": -1.3911504338214946,
    "reason": "SL",
    "regime": "trending",
    "score": "SCORE:-3.0|TRENDING",
    "opened": "2026-03-10 03:00:00",
    "closed": "2026-03-10 15:00:00"
  },
  {
    "symbol": "ETH/USDT",
    "side": "sell",
    "entry": 2075.4717450000003,
    "exit": 2118.1304050000003,
    "qty": 0.0257,
    "pnl": 0.01690583569358106,
    "reason": "SL_HALF",
    "regime": "trending",
    "score": "SCORE:-3.0|TRENDING",
    "opened": "2026-03-11 18:00:00",
    "closed": "2026-03-13 00:00:00"
  },
  {
    "symbol": "ETH/USDT",
    "side": "sell",
    "entry": 2154.78207,
    "exit": 2083.827565,
    "qty": 0.0534,
    "pnl": 2.4024808323772273,
    "reason": "TP",
    "regime": "trending",
    "score": "SCORE:-3.0|TRENDING",
    "opened": "2026-03-21 13:00:00",
    "closed": "2026-03-21 23:00:00"
  },
  {
    "symbol": "ETH/USDT",
    "side": "sell",
    "entry": 2046.6661550000001,
    "exit": 2133.7126100000005,
    "qty": 0.0327,
    "pnl": -2.928438109869312,
    "reason": "SL",
    "regime": "trending",
    "score": "SCORE:-3.0|TRENDING",
    "opened": "2026-03-23 01:00:00",
    "closed": "2026-03-23 11:00:00"
  },
  {
    "symbol": "ETH/USDT",
    "side": "sell",
    "entry": 2108.115415,
    "exit": 2155.151885,
    "qty": 0.0277,
    "pnl": -1.3737657215260002,
    "reason": "SL",
    "regime": "trending",
    "score": "SCORE:-3.5|TRENDING",
    "opened": "2026-03-24 17:00:00",
    "closed": "2026-03-24 23:00:00"
  },
  {
    "symbol": "ETH/USDT",
    "side": "sell",
    "entry": 2118.4902250000005,
    "exit": 1990.6741650000001,
    "qty": 0.0347,
    "pnl": 2.7523553320600547,
    "reason": "TP",
    "regime": "trending",
    "score": "SCORE:-3.5|TRENDING",
    "opened": "2026-03-26 05:00:00",
    "closed": "2026-03-27 10:00:00"
  },
  {
    "symbol": "ETH/USDT",
    "side": "sell",
    "entry": 1995.691655,
    "exit": 2025.3868000000002,
    "qty": 0.0518,
    "pnl": -1.6631836293814073,
    "reason": "SL",
    "regime": "trending",
    "score": "SCORE:-3.0|TRENDING",
    "opened": "2026-03-28 10:00:00",
    "closed": "2026-03-28 13:00:00"
  },
  {
    "symbol": "ETH/USDT",
    "side": "sell",
    "entry": 2005.5067450000001,
    "exit": 2009.4247850000002,
    "qty": 0.0554,
    "pnl": 0.3970695626369758,
    "reason": "SL_HALF",
    "regime": "trending",
    "score": "SCORE:-3.0|TRENDING",
    "opened": "2026-03-29 21:00:00",
    "closed": "2026-03-30 01:00:00"
  },
  {
    "symbol": "ETH/USDT",
    "side": "sell",
    "entry": 2313.432705,
    "exit": 2369.1548300000004,
    "qty": 0.0347,
    "pnl": -2.031049209978708,
    "reason": "SL",
    "regime": "trending",
    "score": "SCORE:-4.0|TRENDING",
    "opened": "2026-04-21 04:00:00",
    "closed": "2026-04-22 02:00:00"
  },
  {
    "symbol": "ETH/USDT",
    "side": "sell",
    "entry": 2304.157345,
    "exit": 2345.0269,
    "qty": 0.0316,
    "pnl": -1.3796264712851927,
    "reason": "SL",
    "regime": "trending",
    "score": "SCORE:-3.0|TRENDING",
    "opened": "2026-04-23 18:00:00",
    "closed": "2026-04-26 14:00:00"
  },
  {
    "symbol": "ETH/USDT",
    "side": "sell",
    "entry": 2313.592625,
    "exit": 2326.1563400000005,
    "qty": 0.0396,
    "pnl": 0.2531405318531063,
    "reason": "SL_HALF",
    "regime": "trending",
    "score": "SCORE:-3.0|TRENDING",
    "opened": "2026-04-27 14:00:00",
    "closed": "2026-04-29 04:00:00"
  },
  {
    "symbol": "ETH/USDT",
    "side": "sell",
    "entry": 2241.63862,
    "exit": 2281.728565,
    "qty": 0.0303,
    "pnl": -1.2969601489232914,
    "reason": "SL",
    "regime": "trending",
    "score": "SCORE:-3.0|TRENDING",
    "opened": "2026-04-30 05:00:00",
    "closed": "2026-05-01 03:00:00"
  },
  {
    "symbol": "ETH/USDT",
    "side": "sell",
    "entry": 2303.28778,
    "exit": 2327.1158600000003,
    "qty": 0.0481,
    "pnl": -1.279764097050411,
    "reason": "SL",
    "regime": "trending",
    "score": "SCORE:-3.0|TRENDING",
    "opened": "2026-05-02 03:00:00",
    "closed": "2026-05-03 14:00:00"
  },
  {
    "symbol": "ETH/USDT",
    "side": "sell",
    "entry": 2313.6625900000004,
    "exit": 2346.38622,
    "qty": 0.0495,
    "pnl": -1.7582231346569754,
    "reason": "SL",
    "regime": "trending",
    "score": "SCORE:-5.0|TRENDING",
    "opened": "2026-05-09 05:00:00",
    "closed": "2026-05-10 15:00:00"
  },
  {
    "symbol": "ETH/USDT",
    "side": "sell",
    "entry": 2310.254295,
    "exit": 2315.48168,
    "qty": 0.0382,
    "pnl": 0.37714118294238924,
    "reason": "SL_HALF",
    "regime": "trending",
    "score": "SCORE:-4.5|TRENDING",
    "opened": "2026-05-12 01:00:00",
    "closed": "2026-05-13 08:00:00"
  },
  {
    "symbol": "ETH/USDT",
    "side": "sell",
    "entry": 2256.6711000000005,
    "exit": 2285.846505,
    "qty": 0.0423,
    "pnl": -1.3494087283148788,
    "reason": "SL",
    "regime": "trending",
    "score": "SCORE:-3.0|TRENDING",
    "opened": "2026-05-14 09:00:00",
    "closed": "2026-05-14 14:00:00"
  },
  {
    "symbol": "ETH/USDT",
    "side": "sell",
    "entry": 2224.257315,
    "exit": 2168.09541,
    "qty": 0.0533,
    "pnl": 1.9399266880849981,
    "reason": "TP",
    "regime": "trending",
    "score": "SCORE:-3.0|TRENDING",
    "opened": "2026-05-16 05:00:00",
    "closed": "2026-05-17 01:00:00"
  },
  {
    "symbol": "ETH/USDT",
    "side": "sell",
    "entry": 2119.75959,
    "exit": 2149.9344950000004,
    "qty": 0.0418,
    "pnl": -1.3683949566518128,
    "reason": "SL",
    "regime": "trending",
    "score": "SCORE:-3.0|TRENDING",
    "opened": "2026-05-18 07:00:00",
    "closed": "2026-05-18 12:00:00"
  },
  {
    "symbol": "ETH/USDT",
    "side": "sell",
    "entry": 2064.817075,
    "exit": 2073.232865,
    "qty": 0.0381,
    "pnl": 0.3225810799865937,
    "reason": "SL_HALF",
    "regime": "trending",
    "score": "SCORE:-3.0|TRENDING",
    "opened": "2026-05-22 23:00:00",
    "closed": "2026-05-23 18:00:00"
  },
  {
    "symbol": "ETH/USDT",
    "side": "sell",
    "entry": 2069.5547050000005,
    "exit": 2098.800075,
    "qty": 0.042,
    "pnl": -1.333348080455985,
    "reason": "SL",
    "regime": "trending",
    "score": "SCORE:-4.5|TRENDING",
    "opened": "2026-05-24 21:00:00",
    "closed": "2026-05-24 23:00:00"
  },
  {
    "symbol": "ETH/USDT",
    "side": "sell",
    "entry": 2111.953495,
    "exit": 2126.49622,
    "qty": 0.0482,
    "pnl": 0.10388368963004269,
    "reason": "SL_HALF",
    "regime": "trending",
    "score": "SCORE:-3.0|TRENDING",
    "opened": "2026-05-25 23:00:00",
    "closed": "2026-05-26 10:00:00"
  },
  {
    "symbol": "ETH/USDT",
    "side": "sell",
    "entry": 2061.58869,
    "exit": 1980.559225,
    "qty": 0.0398,
    "pnl": 2.088125246780902,
    "reason": "TP",
    "regime": "trending",
    "score": "SCORE:-4.5|TRENDING",
    "opened": "2026-05-27 14:00:00",
    "closed": "2026-05-28 03:00:00"
  },
  {
    "symbol": "ETH/USDT",
    "side": "sell",
    "entry": 2001.77861,
    "exit": 2030.60419,
    "qty": 0.0406,
    "pnl": -1.2685473930079978,
    "reason": "SL",
    "regime": "trending",
    "score": "SCORE:-3.0|TRENDING",
    "opened": "2026-05-29 03:00:00",
    "closed": "2026-05-29 15:00:00"
  },
  {
    "symbol": "ETH/USDT",
    "side": "sell",
    "entry": 2007.0559700000001,
    "exit": 1967.6456850000002,
    "qty": 0.077,
    "pnl": 1.9294291785552524,
    "reason": "TP",
    "regime": "trending",
    "score": "SCORE:-3.5|TRENDING",
    "opened": "2026-05-31 14:00:00",
    "closed": "2026-06-01 14:00:00"
  },
  {
    "symbol": "ETH/USDT",
    "side": "sell",
    "entry": 1905.78663,
    "exit": 1780.5492800000002,
    "qty": 0.027,
    "pnl": 2.2146853537665594,
    "reason": "TP",
    "regime": "trending",
    "score": "SCORE:-3.0|TRENDING",
    "opened": "2026-06-02 20:00:00",
    "closed": "2026-06-03 20:00:00"
  },
  {
    "symbol": "ETH/USDT",
    "side": "sell",
    "entry": 1773.9925600000001,
    "exit": 1614.2324800000001,
    "qty": 0.0232,
    "pnl": 2.4017885512985773,
    "reason": "TP",
    "regime": "trending",
    "score": "SCORE:-4.0|TRENDING",
    "opened": "2026-06-04 20:00:00",
    "closed": "2026-06-05 13:00:00"
  },
  {
    "symbol": "ETH/USDT",
    "side": "sell",
    "entry": 1556.9211500000001,
    "exit": 1614.3724100000002,
    "qty": 0.0211,
    "pnl": -1.2523701624696009,
    "reason": "SL",
    "regime": "trending",
    "score": "SCORE:-3.0|TRENDING",
    "opened": "2026-06-06 14:00:00",
    "closed": "2026-06-07 07:00:00"
  },
  {
    "symbol": "ETH/USDT",
    "side": "sell",
    "entry": 1702.66824,
    "exit": 1717.8106650000002,
    "qty": 0.0315,
    "pnl": 0.3055155912458627,
    "reason": "SL_HALF",
    "regime": "trending",
    "score": "SCORE:-3.0|TRENDING",
    "opened": "2026-06-08 21:00:00",
    "closed": "2026-06-14 21:00:00"
  }
]